simhash/__init__.py
simhash-2.1.2.dist-info/LICENSE
simhash-2.1.2.dist-info/METADATA
simhash-2.1.2.dist-info/WHEEL
simhash-2.1.2.dist-info/top_level.txt
simhash-2.1.2.dist-info/RECORD
